{
"data" : [
    {
      "rname": "Coloumn Completeness",
      "rtype": "Data Accuracy / completeness",
      "priority": 1,
      "comments": 2,
      "exceptions": 3
    },
    {
      "rname": "Gav Nav",
      "rtype": "Data Accuracy / completeness",
      "priority": 3,
      "comments": 2,
      "exceptions": 3
    },
    {
      "rname": "Fund Completeness",
      "rtype": "Data Accuracy / completeness",
      "priority": 3,
      "comments": 2,
      "exceptions": 3
    },
    {
      "rname": "Data Type",
      "rtype": "Data Accuracy / completeness",
      "priority": 2,
      "comments": 2,
      "exceptions": 3
    },
    {
      "rname": "Maturity Date",
      "rtype": "Data Accuracy / completeness",
      "priority": 1,
      "comments": 2,
      "exceptions": 500
    },
    {
      "rname": "Coloumn Completeness",
      "rtype": "Data Accuracy / completeness",
      "priority": 2,
      "comments": 2,
      "exceptions": 3
    },
    {
      "rname": "Coloumn Completeness",
      "rtype": "Data Accuracy / completeness",
      "priority": 1,
      "comments": 2,
      "exceptions": 3
    },
    {
      "rname": "Coloumn Completeness",
      "rtype": "Data Accuracy / completeness",
      "priority": 1,
      "comments": 2,
      "exceptions": 3
    },
    {
      "rname": "Coloumn Completeness",
      "rtype": "Data Accuracy / completeness",
      "priority": 1,
      "comments": 2,
      "exceptions": 3
    },
    {
      "rname": "Coloumn Completeness",
      "rtype": "Data Accuracy / completeness",
      "priority": 1,
      "comments": 2,
      "exceptions": 3
    }

  ]
}